hopper/__init__.py
hopper/__main__.py
hopper/__version__.py
hopper/hopper.py
hopper/parser.py
hopper/utils.py
hopper-0.0.1.dist-info/LICENSE.md
hopper-0.0.1.dist-info/METADATA
hopper-0.0.1.dist-info/WHEEL
hopper-0.0.1.dist-info/entry_points.txt
hopper-0.0.1.dist-info/top_level.txt
hopper-0.0.1.dist-info/RECORD
