Metadata-Version: 2.1
Name: hopper
Version: 0.0.1
Summary: A Python package to inspect an eml message received from hops
Home-page: https://github.com/msadministrator/hopper
Author: MSAdministrator
Author-email: rickardja@live.com
License: MIT
Keywords: eml,hop,received from,email
Platform: UNKNOWN
Requires-Python: >=2.6, !=3.0.*, !=3.1.*, !=3.2.*, <4
Requires-Dist: dateparser (==0.6.0)
Requires-Dist: pytz (==2020.1)
Requires-Dist: fire
